{"id":"d0006e77-dc45-ec45-02de-b4799b83ac94","name":"AchillesDemo_Scenario8","timestamp":1368134353413,"requests":[{"collectionId":"d0006e77-dc45-ec45-02de-b4799b83ac94","id":"0d11a8cd-b3b8-7691-51c2-97bc1b87fdcb","name":"05_Richard_favoriteline","description":"","url":"{{url}}/achillesTwitter/favoriteline?userLogin=rsmith&length=10","method":"GET","headers":"Accept: application/json\n","data":"","dataMode":"raw","timestamp":0,"responses":[],"version":2},{"collectionId":"d0006e77-dc45-ec45-02de-b4799b83ac94","id":"136ee4a0-460e-4f8a-e39b-bac5f1923304","name":"01_John_timeline","description":"","url":"{{url}}/achillesTwitter/timeline?userLogin=jdoe&length=10","method":"GET","headers":"Accept: application/json\n","data":[],"dataMode":"params","timestamp":0,"responses":[],"version":2},{"collectionId":"d0006e77-dc45-ec45-02de-b4799b83ac94","id":"1dfe7569-b1b2-76e0-7bd4-d43066463db6","name":"02_John_removes_tweet2","description":"","url":"{{url}}/achillesTwitter/tweet?tweetId=xxx","method":"DELETE","headers":"Accept: application/json\n","data":"","dataMode":"raw","timestamp":0,"responses":[],"version":2},{"collectionId":"d0006e77-dc45-ec45-02de-b4799b83ac94","id":"460a3904-70d2-8618-87cb-30c631aacf7b","name":"03_John_removes_tweet3","description":"","url":"{{url}}/achillesTwitter/tweet?tweetId=xxx","method":"DELETE","headers":"Accept: application/json\n","data":"","dataMode":"raw","timestamp":0,"responses":[],"version":2},{"collectionId":"d0006e77-dc45-ec45-02de-b4799b83ac94","id":"5b56555a-f10a-0786-a662-5029893c3a17","name":"04_Helen_favoriteline","description":"","url":"{{url}}/achillesTwitter/favoriteline?userLogin=hsue&length=10","method":"GET","headers":"Accept: application/json\n","data":"","dataMode":"raw","timestamp":0,"responses":[],"version":2},{"collectionId":"d0006e77-dc45-ec45-02de-b4799b83ac94","id":"b05f95bf-6dba-847a-f462-4419b4f2b1eb","name":"06_Get_info_on_John","description":"","url":"{{url}}/achillesTwitter/user?userLogin=jdoe","method":"GET","headers":"Accept: application/json\n","data":"","dataMode":"raw","timestamp":0,"responses":[],"version":2}]}